{
  "total": 31,
  "max_score": 1.4157969,
  "hits": [{
    "_id": "DE:Mauswiesel.HE:1341273",
    "_score": 1.4157969,
    "_source": {
      "lom:technical_location": "http://lernarchiv.bildung.hessen.de/grundschule/Sachunterricht/tiere/waldtiere/igel/Igel.html",
      "lom:creator": ["Friedhelm Schumacher"],
      "lom:educational_context": ["compulsory education", "primary school"],
      "lom:provider": ["Hessischer Bildungsserver"],
      "ll3:context": ["Allgemeinbildende Schule", "Primarstufe"],
      "ll3:classificationDisciplineEntry": ["Allgemeine Zoologie", "Biologie", "Grundschule", "Haustiere, Nutztiere", "Sachkunde", "Säugetiere", "Tiere", "Tiermonographie", "Wildlebende Tiere", "Wirbeltiere", "Zoologie"],
      "lom:classificationDisciplineEntry": ["Allgemeine Zoologie", "Tiermonographie", "Wildlebende Tiere"],
      "ll3:learningResourceType": ["Anderer Ressourcentyp"],
      "lom:header_datestamp": "2015-09-11T08:15:24Z",
      "lom:header_identifier": "DE:Mauswiesel.HE:1341273",
      "lom:educational_learningResourceType": ["other"],
      "ll3:classificationDisciplineId": ["080", "08005", "0800501", "0800504", "080050405", "08005040502", "280", "28010", "2801016", "280101601", "28010160101"],
      "lom:providerDate": ["2015-09-11T10:15:24+02:00"],
      "lom:rights_de": "Diese Ressource kann für unterrichtliche Zwecke genutzt werden.",
      "importDate": "2016-03-01T00:00:00+01:00",
      "lom:creatorDate": ["2015-09-11T10:15:24+02:00"],
      "lom:general_title": "Igel",
      "lom:general_description": "Beschäftigung mit dem Igel. Wie lebt der Igel? Was macht er im Winter? Wovon ernährt er sich?",
      "lom:general_keyword": ["igel"],
      "lom:general_language": ["de"],
      "lom:classificationDisciplineId": ["0800501", "08005040502", "28010160101"],
      "lom:relation_hasThumbnail": ["http://lernarchiv.bildung.hessen.de/logo_thumbs/hessen-bs.gif"]
    }
  }, {
    "_id": "CP.planetschule-746",
    "_score": 0.7252457,
    "_source": {
      "lom:technical_location": "http://www.planet-schule.de/sf/php/02_sen01.php?sendung=746",
      "lom:provider": ["Planet Schule / SWR"],
      "lom:classificationDisciplineEntry": ["Wildlebende Tiere", "Wildtiere"],
      "ll3:learningResourceType": ["Video"],
      "lom:header_identifier": "CP.planetschule-746",
      "lom:educational_typicalAgeRange": ["6-15"],
      "lom:rights_de": "frei für die unterrichtliche Nutzung",
      "ll3:classificationDisciplineId": ["080", "08005", "0800504", "080050405", "08005040502", "280", "28010", "2801016", "280101602"],
      "lom:ispartof": ["BWS-04980047"],
      "lom:general_description": "Die Sendung beschreibt den Igel als nachtaktives Säugetier, das erst in der Abenddämmerung sein Nest verlässt, um nach Fressen zu suchen. Weitere Schwerpunkte: Orientierung, das Auto als Feind Nr. 1, Paarung, Aufzucht der Jungen und Überwinterung.",
      "lom:general_keyword": ["Igel", "Säugetiere", "Tierbeobachtung", "Verhalten ( Tier)"],
      "lom:publisherDate": ["1995-11-30T01:00:00+01:00"],
      "lom:classificationDisciplineId": ["08005040502", "280101602"],
      "lom:educational_context": ["compulsory education", "lower secondary school", "primary school", "special education"],
      "lom:creator": ["Friedhelm Schumacher"],
      "lom:publisher": ["SWR (Baden-Baden)"],
      "ll3:context": ["Allgemeinbildende Schule", "Primarstufe", "Sekundarstufe I", "Sonderpädagogische Förderung"],
      "lom:technical_format": "text/html",
      "ll3:classificationDisciplineEntry": ["Biologie", "Grundschule", "Sachkunde", "Säugetiere", "Tiere", "Wildlebende Tiere", "Wildtiere", "Wirbeltiere", "Zoologie"],
      "lom:header_datestamp": "2015-09-18T14:23:55Z",
      "lom:educational_learningResourceType": ["video"],
      "lom:providerDate": ["2015-09-18T16:23:55+02:00"],
      "lom:educational_intendedEndUserRole": ["learner"],
      "importDate": "2016-03-01T00:00:00+01:00",
      "lom:creatorDate": ["2015-09-18T16:23:55+02:00"],
      "lom:general_title": "Jäger in der Nacht - Der Igel",
      "lom:general_language": ["de"],
      "lom:relation_hasThumbnail": ["http://www.planet-schule.de/sf/css/img/logo_ps_14_2x.png"]
    }
  }, {
    "_id": "LEARNLINE-00003496",
    "_score": 0.6879954,
    "_source": {
      "lom:technical_location": "http://www.tierchenwelt.de/tier-spiele/malvorlagen/2232-malvorlage-igel.html",
      "lom:provider": ["learn:line NRW"],
      "lom:classificationDisciplineEntry": ["Kreatives, künstlerisches Lernen", "Kunst, Werken, Textiles Gestalten", "Malen, Basteln", "Spiele", "Tiere"],
      "ll3:learningResourceType": ["Bild", "Simulation", "Werkzeug"],
      "lom:header_identifier": "LEARNLINE-00003496",
      "lom:educational_typicalAgeRange": ["6-9"],
      "lom:rights_de": "Diese Ressource kann für unterrichtliche Zwecke genutzt werden (keine kommerzielle Nutzung).",
      "ll3:classificationDisciplineId": ["140", "14008", "280", "28006", "28010", "2801016", "360", "36006", "36007"],
      "lom:ispartof": ["LEARNLINE-00005350"],
      "lom:general_description": "Interaktive Malvorlage auf tierchenwelt.de mit einem Igel als Motiv. Die Malvorlage kann farbig ausgemalt, mit Stempeln verziert, ausgedruckt, abgespeichert und in eine Malvorlagen-Galerie eingereicht werden. Das Ausmalbild kann sowohl online am PC ausgemalt werden, als auch unterwegs auf Tablet-PC und Smartphone.",
      "lom:general_keyword": ["Ausmalbild", "Ausmalbilder", "Igel", "Malvorlage", "Malvorlagen", "Tierchenwelt", "interaktiv", "online ausmalen", "online zeichnen", "zeichnen"],
      "lom:publisherDate": ["2012-11-30T01:00:00+01:00"],
      "lom:ischildof": "learnline|:|:|:|LEARNLINE-00005350",
      "lom:classificationDisciplineId": ["14008", "28006", "2801016", "36006", "36007"],
      "lom:creator": ["Silke Menne"],
      "lom:educational_context": ["compulsory education", "pre-school", "primary school"],
      "lom:publisher": ["tierchenwelt.de"],
      "lom:classificationCompetencyId": ["09010401"],
      "ll3:context": ["Allgemeinbildende Schule", "Elementarbildung", "Primarstufe"],
      "lom:technical_format": "text/html",
      "lom:classificationCompetencyEntry": ["Medien kreativ zu nutzen, um eigene Ideen und Themen darzustellen (z.B. Fotocollage, Daumenkino, Hörspiel)."],
      "ll3:classificationDisciplineEntry": ["Elementarbereich, Vorschulerziehung", "Grundschule", "Kinder- und Jugendbildung", "Kreatives, künstlerisches Lernen", "Kunst, Werken, Textiles Gestalten", "Malen, Basteln", "Sachkunde", "Spiele", "Tiere"],
      "ll3:classificationCompetencyEntry": ["Elementarbereich", "Medien kreativ zu nutzen, um eigene Ideen und Themen darzustellen (z.B. Fotocollage, Daumenkino, Hörspiel).", "Produzieren und Präsentieren"],
      "lom:header_datestamp": "2015-11-01T12:10:19Z",
      "lom:rights": "keine Angabe",
      "lom:educational_learningResourceType": ["image", "simulation", "tool"],
      "lom:providerDate": ["2015-11-01T13:10:19+01:00"],
      "importDate": "2016-03-01T00:00:00+01:00",
      "lom:educational_intendedEndUserRole": ["learner"],
      "lom:creatorDate": ["2015-11-01T13:10:19+01:00"],
      "lom:general_title": "Malvorlage / Ausmalbild: Igel - Interaktiv",
      "ll3:classificationCompetencyId": ["0901", "090104", "09010401"],
      "lom:general_language": ["de"],
      "lom:relation_hasThumbnail": ["http://www.tierchenwelt.de/images/stories/illustrationen/malvorlagen/Vorschau_Icons/Igel.png"]
    }
  }, {
    "_id": "LEARNLINE-00004758",
    "_score": 0.5698126,
    "_source": {
      "lom:technical_location": "http://www.tierchenwelt.de/insektenfresser/68-igel.html",
      "lom:provider": ["learn:line NRW"],
      "lom:classificationDisciplineEntry": ["Allgemeine Zoologie", "Säugetiere", "Tiere"],
      "ll3:learningResourceType": ["Bild", "Text"],
      "lom:header_identifier": "LEARNLINE-00004758",
      "lom:educational_typicalAgeRange": ["6-15"],
      "ll3:classificationDisciplineId": ["080", "08005", "0800501", "0800504", "080050405", "280", "28010", "2801016"],
      "lom:rights_de": "Texte und Illustrationen können für unterrichtliche Zwecke frei genutzt werden (keine kommerzielle Nutzung). Die Fotos sind möglicherweise lizenzrechtlich geschützt. Bei Fragen bitte Kontakt aufnehmen.",
      "lom:ispartof": ["LEARNLINE-00005350"],
      "lom:general_description": "Tier-Steckbrief mit spannenden Wissenshäppchen, allen wichtigen Infos und Eckdaten (Größe, Gewicht, Ernährung, Lebensraum, Lebensdauer etc.). Für Kinder verständlich erklärt.",
      "lom:general_keyword": ["Igel", "Insektenfresser", "Stachelkleid", "Stacheln", "Steckbrief", "Tierchenwelt"],
      "lom:publisherDate": ["2013-11-30T01:00:00+01:00"],
      "lom:ischildof": "learnline|:|:|:|LEARNLINE-00005350",
      "lom:classificationDisciplineId": ["0800501", "080050405", "2801016"],
      "lom:educational_context": ["compulsory education", "lower secondary school", "pre-school", "primary school"],
      "lom:creator": ["Silke Menne"],
      "lom:publisher": ["tierchenwelt.de"],
      "ll3:context": ["Allgemeinbildende Schule", "Elementarbildung", "Primarstufe", "Sekundarstufe I"],
      "lom:technical_format": "text/html",
      "ll3:classificationDisciplineEntry": ["Allgemeine Zoologie", "Biologie", "Grundschule", "Sachkunde", "Säugetiere", "Tiere", "Wirbeltiere", "Zoologie"],
      "lom:header_datestamp": "2014-05-02T12:31:21Z",
      "lom:educational_learningResourceType": ["image", "text"],
      "lom:providerDate": ["2014-05-02T14:31:21+02:00"],
      "lom:educational_intendedEndUserRole": ["learner", "teacher"],
      "importDate": "2016-03-01T00:00:00+01:00",
      "lom:general_title": "Igel - Steckbrief",
      "lom:creatorDate": ["2014-05-02T14:31:21+02:00"],
      "lom:general_language": ["de"],
      "lom:relation_hasThumbnail": ["http://www.tierchenwelt.de/images/stories/illustrationen/tier-steckbrief.png"]
    }
  }, {
    "_id": "DE:Mauswiesel.HE:1299259",
    "_score": 0.40731725,
    "_source": {
      "lom:technical_location": "http://lernarchiv.bildung.hessen.de/grundschule/Deutsch/Projekte/maerchen/maerchen_hoeren/gebrueder_grimm/edu_1319717415.html",
      "lom:creator": ["Friedhelm Schumacher"],
      "lom:educational_context": ["compulsory education", "primary school"],
      "lom:provider": ["Hessischer Bildungsserver"],
      "ll3:context": ["Allgemeinbildende Schule", "Primarstufe"],
      "ll3:classificationDisciplineEntry": ["Deutsch", "Epik", "Grundschule", "Literatur", "Märchen, Sagen"],
      "lom:classificationDisciplineEntry": ["Epik", "Märchen, Sagen"],
      "ll3:learningResourceType": ["Anderer Ressourcentyp"],
      "lom:header_datestamp": "2012-01-16T22:12:07Z",
      "lom:header_identifier": "DE:Mauswiesel.HE:1299259",
      "lom:educational_typicalAgeRange": ["6-9"],
      "lom:educational_learningResourceType": ["other"],
      "lom:rights_de": "Diese Ressource kann für unterrichtliche Zwecke genutzt werden.",
      "lom:providerDate": ["2012-01-16T23:12:07+01:00"],
      "ll3:classificationDisciplineId": ["120", "12001", "1200101", "280", "28001", "2800102", "280010201"],
      "importDate": "2016-03-01T00:00:00+01:00",
      "lom:educational_intendedEndUserRole": ["student", "teacher"],
      "lom:general_title": "Der Hase und der Igel",
      "lom:creatorDate": ["2012-01-16T23:12:07+01:00"],
      "lom:general_description": "Der Hase und der Igel - ein Märchen der Gebrüder Grimm",
      "lom:general_keyword": ["hase"],
      "lom:general_language": ["de"],
      "lom:relation_hasThumbnail": ["http://dms.bildung.hessen.de/dms_media/image/exercisefolder/mauswiesel/ergebnis_platzhalter.jpg"],
      "lom:classificationDisciplineId": ["1200101", "280010201"]
    }
  }, {
    "_id": "RP-07954826",
    "_score": 0.38472655,
    "_source": {
      "lom:technical_location": "http://www.kindernetz.de/oli/tierlexikon/igel/-/id=74994/nid=74994/did=82114/1em3xn4/index.html",
      "lom:provider": ["Omega RLP"],
      "lom:classificationDisciplineEntry": ["Haltung und Pflege", "Säugetiere", "Tiermonographie"],
      "ll3:learningResourceType": ["Text", "Website"],
      "lom:header_identifier": "RP-07954826",
      "lom:educational_typicalAgeRange": ["Array"],
      "ll3:classificationDisciplineId": ["080", "08005", "0800504", "080050405", "280", "28010", "2801016", "280101601", "28010160101", "28010160102"],
      "lom:rights_de": "Wiedergabe; Nutzung im unterrichtlcihen Kontext ohne Recht zur Weiterverbreitung",
      "lom:ispartof": ["RP-05555686"],
      "lom:general_description": "Der Link führt zum Online-Steckbrief des im Titel genannten Tiers. Der Steckbrief ist auch für Kinder verständlich. Er enthält Bilder zum Tier, nennt die wesentlichen Merkmale, nennt den lateinischen Namen des Tieres und beinhaltet Hinweise zu Verhalten und Pflege.",
      "lom:general_keyword": ["Afrikanischer Weißbauchigel", "Erinaceus europaeus", "Höhle", "Igel", "Insektenfresser", "Knopfaugen", "Schlangen", "Stacheln", "Stummelschwanz", "Winterschlaf", "Würmer"],
      "lom:classificationDisciplineId": ["080050405", "28010160101", "28010160102"],
      "lom:educational_context": ["compulsory education", "lower secondary school", "pre-school", "primary school"],
      "lom:creator": ["Boris Bockelmann"],
      "lom:publisher": ["Südwestrundfunk"],
      "ll3:context": ["Allgemeinbildende Schule", "Elementarbildung", "Primarstufe", "Sekundarstufe I"],
      "lom:technical_format": "text/html",
      "ll3:classificationDisciplineEntry": ["Biologie", "Grundschule", "Haltung und Pflege", "Haustiere, Nutztiere", "Sachkunde", "Säugetiere", "Tiere", "Tiermonographie", "Wirbeltiere", "Zoologie"],
      "lom:header_datestamp": "2014-04-04T10:25:11Z",
      "lom:educational_learningResourceType": ["text", "web page"],
      "lom:providerDate": ["2014-04-04T12:25:11+02:00"],
      "lom:educational_intendedEndUserRole": ["learner"],
      "importDate": "2016-03-01T00:00:00+01:00",
      "lom:general_title": "Igel - Steckbrief",
      "lom:creatorDate": ["2014-04-04T12:25:11+02:00"],
      "lom:general_language": ["de"],
      "lom:relation_hasThumbnail": ["http://www.kindernetz.de/-/id=197468/property=detail/width=220/height=165/pubVersion=1/1yipd77/index.jpg"]
    }
  }, {
    "_id": "DE:Mauswiesel.HE:169929",
    "_score": 0.37343743,
    "_source": {
      "lom:technical_location": "http://www.primolo.de/home/Igelzeitung/",
      "lom:creator": ["Friedhelm Schumacher"],
      "lom:educational_context": ["compulsory education", "primary school"],
      "lom:provider": ["Hessischer Bildungsserver"],
      "ll3:context": ["Allgemeinbildende Schule", "Primarstufe"],
      "ll3:classificationDisciplineEntry": ["Allgemeine Zoologie", "Biologie", "Grundschule", "Haustiere, Nutztiere", "Sachkunde", "Säugetiere", "Tiere", "Tiermonographie", "Wildlebende Tiere", "Wirbeltiere", "Zoologie"],
      "lom:classificationDisciplineEntry": ["Allgemeine Zoologie", "Tiermonographie", "Wildlebende Tiere"],
      "ll3:learningResourceType": ["Anderer Ressourcentyp"],
      "lom:header_datestamp": "2012-01-16T22:10:14Z",
      "lom:header_identifier": "DE:Mauswiesel.HE:169929",
      "lom:educational_typicalAgeRange": ["7-9"],
      "lom:educational_learningResourceType": ["other"],
      "ll3:classificationDisciplineId": ["080", "08005", "0800501", "0800504", "080050405", "08005040502", "280", "28010", "2801016", "280101601", "28010160101"],
      "lom:providerDate": ["2012-01-16T23:10:14+01:00"],
      "lom:rights_de": "Diese Ressource kann für unterrichtliche Zwecke genutzt werden.",
      "lom:educational_intendedEndUserRole": ["student", "teacher"],
      "importDate": "2016-03-01T00:00:00+01:00",
      "lom:creatorDate": ["2012-01-16T23:10:14+01:00"],
      "lom:general_title": "Steckbrief: Igel",
      "lom:general_description": "Einen von Kindern gestalteten Steckbrief über Igel finden Sie hier auf den Seiten von Primolo.",
      "lom:general_keyword": ["Steckbriefe", "tiere_wald_feld"],
      "lom:general_language": ["de"],
      "lom:classificationDisciplineId": ["0800501", "08005040502", "28010160101"],
      "lom:relation_hasThumbnail": ["http://dms.bildung.hessen.de/dms_media/image/exercisefolder/mauswiesel/ergebnis_platzhalter.jpg"]
    }
  }, {
    "_id": "DE:Mauswiesel.HE:125013",
    "_score": 0.3339486,
    "_source": {
      "lom:technical_location": "http://www.kinder-tierlexikon.de/i/igel.htm",
      "lom:creator": ["Friedhelm Schumacher"],
      "lom:educational_context": ["compulsory education", "primary school"],
      "lom:provider": ["Hessischer Bildungsserver"],
      "ll3:context": ["Allgemeinbildende Schule", "Primarstufe"],
      "ll3:classificationDisciplineEntry": ["Allgemeine Zoologie", "Biologie", "Grundschule", "Haustiere, Nutztiere", "Sachkunde", "Säugetiere", "Tiere", "Tiermonographie", "Wildlebende Tiere", "Wirbeltiere", "Zoologie"],
      "lom:classificationDisciplineEntry": ["Allgemeine Zoologie", "Tiermonographie", "Wildlebende Tiere"],
      "ll3:learningResourceType": ["Anderer Ressourcentyp"],
      "lom:header_datestamp": "2012-01-16T22:10:14Z",
      "lom:header_identifier": "DE:Mauswiesel.HE:125013",
      "lom:educational_typicalAgeRange": ["8-9"],
      "lom:educational_learningResourceType": ["other"],
      "ll3:classificationDisciplineId": ["080", "08005", "0800501", "0800504", "080050405", "08005040502", "280", "28010", "2801016", "280101601", "28010160101"],
      "lom:providerDate": ["2012-01-16T23:10:14+01:00"],
      "lom:rights_de": "Frei nutzbar",
      "lom:educational_intendedEndUserRole": ["student", "teacher"],
      "importDate": "2016-03-01T00:00:00+01:00",
      "lom:creatorDate": ["2012-01-16T23:10:14+01:00"],
      "lom:general_title": "Der Igel im kinder-tierlexikon.de",
      "lom:general_description": "Auf den Seiten des kinder-tierlexikon.de finden SchülerInnen Hintergrundinformationen über den Igel.",
      "lom:general_keyword": ["tiere_wald_feld"],
      "lom:general_language": ["de"],
      "lom:classificationDisciplineId": ["0800501", "08005040502", "28010160101"],
      "lom:relation_hasThumbnail": ["http://dms.bildung.hessen.de/dms_media/image/exercisefolder/mauswiesel/ergebnis_platzhalter.jpg"]
    }
  }, {
    "_id": "SN-02950136",
    "_score": 0.3302849,
    "_source": {
      "lom:technical_location": "http://vorleser.net/tucholsky_wenn_die_igel/hoerbuch.html",
      "lom:provider": ["MeSax"],
      "lom:classificationDisciplineEntry": ["20. Jahrhundert", "Lyrik"],
      "ll3:learningResourceType": ["Audio"],
      "lom:header_identifier": "SN-02950136",
      "lom:educational_typicalAgeRange": ["17-18"],
      "ll3:classificationDisciplineId": ["120", "12001", "1200103", "1200105", "120010505"],
      "lom:ispartof": ["BY-00009519"],
      "lom:general_description": "Bernhard Scheller liest das Gedicht \"Wenn die Igel in der Abendstunde\" (2:31 min) von Kurt Tucholsky (1890-1935).",
      "lom:general_keyword": ["Gedicht", "Hörbuch", "Lesung ( für Erwachsene)", "Lesung ( für Jugendliche)", "Tucholsky, Kurt"],
      "lom:publisherDate": ["2007-11-30T01:00:00+01:00"],
      "lom:classificationDisciplineId": ["1200103", "120010505"],
      "lom:educational_context": ["compulsory education", "continuing education", "upper secondary school"],
      "lom:creator": ["Frank Frenzel"],
      "lom:publisher": ["vorleser.net (phonetics group GbR, Leipzig)"],
      "ll3:context": ["Allgemeinbildende Schule", "Erwachsenenbildung", "Sekundarstufe II"],
      "lom:technical_format": "text/html",
      "ll3:classificationDisciplineEntry": ["20. Jahrhundert", "Deutsch", "Literatur", "Literaturgeschichte", "Lyrik"],
      "lom:header_datestamp": "2014-05-05T21:26:21Z",
      "lom:educational_learningResourceType": ["audio"],
      "lom:providerDate": ["2014-05-05T23:26:21+02:00"],
      "lom:educational_intendedEndUserRole": ["learner", "teacher"],
      "importDate": "2016-03-01T00:00:00+01:00",
      "lom:general_title": "Wenn die Igel in der Abendstunde",
      "lom:creatorDate": ["2014-05-05T23:26:21+02:00"],
      "lom:general_language": ["de"],
      "lom:relation_hasThumbnail": ["https://sodis.de/cp/images/vorleser_net.png"]
    }
  }, {
    "_id": "DE:Mauswiesel.HE:169938",
    "_score": 0.31371155,
    "_source": {
      "lom:technical_location": "http://www.medienwerkstatt-online.de/lws_wissen/vorlagen/showcard.php?id=3920&edit=0",
      "lom:creator": ["Friedhelm Schumacher"],
      "lom:educational_context": ["compulsory education", "primary school"],
      "lom:publisher": ["Medienwerkstatt Mühlacker"],
      "lom:provider": ["Hessischer Bildungsserver"],
      "ll3:context": ["Allgemeinbildende Schule", "Primarstufe"],
      "ll3:classificationDisciplineEntry": ["Allgemeine Zoologie", "Biologie", "Grundschule", "Haustiere, Nutztiere", "Sachkunde", "Säugetiere", "Tiere", "Tiermonographie", "Wildlebende Tiere", "Wirbeltiere", "Zoologie"],
      "lom:classificationDisciplineEntry": ["Allgemeine Zoologie", "Tiermonographie", "Wildlebende Tiere"],
      "ll3:learningResourceType": ["Anderer Ressourcentyp"],
      "lom:header_datestamp": "2015-09-11T08:15:31Z",
      "lom:header_identifier": "DE:Mauswiesel.HE:169938",
      "lom:educational_learningResourceType": ["other"],
      "lom:rights_de": "Diese Ressource kann für unterrichtliche Zwecke genutzt werden.",
      "lom:providerDate": ["2015-09-11T10:15:31+02:00"],
      "ll3:classificationDisciplineId": ["080", "08005", "0800501", "0800504", "080050405", "08005040502", "280", "28010", "2801016", "280101601", "28010160101"],
      "importDate": "2016-03-01T00:00:00+01:00",
      "lom:general_title": "Wissenskarte: Igel Fotos",
      "lom:creatorDate": ["2015-09-11T10:15:31+02:00"],
      "lom:general_description": "Auf den Wissenskarten der Medienwerkstatt Mühlacker finden Schülerinnen und Schüler Fotos über den Igel.",
      "lom:general_keyword": ["Fotos"],
      "lom:general_language": ["de"],
      "lom:relation_hasThumbnail": ["http://lernarchiv.bildung.hessen.de/grundschule/Sachunterricht/kinderseiten/mwm-wissen-logo-bg.gif"],
      "lom:classificationDisciplineId": ["0800501", "08005040502", "28010160101"]
    }
  }, {
    "_id": "SN-02950119",
    "_score": 0.3106583,
    "_source": {
      "lom:technical_location": "http://vorleser.net/grimm_haaseigel/hoerbuch.html",
      "lom:provider": ["MeSax"],
      "lom:classificationDisciplineEntry": ["Märchen und Geschichten", "Märchen, Sagen"],
      "ll3:learningResourceType": ["Audio"],
      "lom:header_identifier": "SN-02950119",
      "lom:educational_typicalAgeRange": ["4-10"],
      "ll3:classificationDisciplineId": ["140", "14001", "280", "28001", "2800102", "280010201"],
      "lom:ispartof": ["BY-00009477"],
      "lom:general_description": "Julia Nogli liest das Märchen \"Der Hase und der Igel \" (7:05 min) der Gebrüder Grimm. Ein Märchen aus der berühmten Sammlung Kinder- und Hausmärchen, die von Jacob und Wilhelm Grimm herausgegeben worden ist.",
      "lom:general_keyword": ["Grimm ( Gebrüder)", "Hörbuch", "Lesung ( für Kinder)", "Märchen"],
      "lom:publisherDate": ["2007-11-30T01:00:00+01:00"],
      "lom:classificationDisciplineId": ["14001", "280010201"],
      "lom:educational_context": ["compulsory education", "lower secondary school", "pre-school"],
      "lom:creator": ["49"],
      "lom:publisher": ["vorleser.net (phonetics group GbR, Leipzig)"],
      "ll3:context": ["Allgemeinbildende Schule", "Elementarbildung", "Sekundarstufe I"],
      "lom:technical_format": "text/html",
      "ll3:classificationDisciplineEntry": ["Deutsch", "Elementarbereich, Vorschulerziehung", "Grundschule", "Literatur", "Märchen und Geschichten", "Märchen, Sagen"],
      "lom:header_datestamp": "2014-05-05T14:47:45Z",
      "lom:educational_learningResourceType": ["audio"],
      "lom:providerDate": ["2014-05-05T16:47:45+02:00"],
      "lom:educational_intendedEndUserRole": ["learner", "teacher"],
      "importDate": "2016-03-01T00:00:00+01:00",
      "lom:general_title": "Der Hase und der Igel",
      "lom:creatorDate": ["2014-05-05T16:47:45+02:00"],
      "lom:general_language": ["de"],
      "lom:relation_hasThumbnail": ["https://sodis.de/cp/images/vorleser_net.png"]
    }
  }, {
    "_id": "LEARNLINE-00004275",
    "_score": 0.30935317,
    "_source": {
      "lom:technical_location": "http://www.lerntraining-grundschule.de/natur",
      "lom:provider": ["learn:line NRW"],
      "lom:classificationDisciplineEntry": ["Grundschule", "Pflanzen", "Tiere"],
      "ll3:learningResourceType": ["Simulation"],
      "lom:header_identifier": "LEARNLINE-00004275",
      "lom:educational_typicalAgeRange": ["6-9"],
      "lom:rights_de": "Ohne Anmeldung",
      "ll3:classificationDisciplineId": ["280", "28010", "2801015", "2801016"],
      "lom:ispartof": ["Learnline-00004181"],
      "lom:general_description": "Der Igel, Tierrekorde oder vom Ei zum Frosch - spannende Quizfragen in zwei Schwierigkeitsstufen zu Lehrplanthemen des Sachunterrichts.",
      "lom:general_keyword": ["Amseln", "Frosch", "Huhn", "Igel", "Marienkäfer", "Natur", "Tierrekorde", "Tierrätsel", "Vögel", "Wetter und Waser"],
      "lom:publisherDate": ["2012-11-30T01:00:00+01:00"],
      "lom:classificationDisciplineId": ["280", "2801015", "2801016"],
      "lom:creator": ["Brigitte Schmidtke"],
      "lom:educational_context": ["compulsory education", "primary school"],
      "lom:publisher": ["leseludi.de"],
      "lom:classificationCompetencyId": ["09010101", "09040102", "09040104"],
      "ll3:context": ["Allgemeinbildende Schule", "Primarstufe"],
      "lom:technical_format": "text/html",
      "lom:classificationCompetencyEntry": ["wenden Basisfunktionen des Internets an (z. B. Angabe der vollständigen URL, Nutzung von Links, Suchmaschinen).", "wenden Basisfunktionen digitaler Medien (z. B. Computer, digitaler Fotoapparat) an."],
      "ll3:classificationDisciplineEntry": ["Grundschule", "Pflanzen", "Sachkunde", "Tiere"],
      "ll3:classificationCompetencyEntry": ["Bedienen und Anwenden", "wenden Basisfunktionen des Internets an (z. B. Angabe der vollständigen URL, Nutzung von Links, Suchmaschinen).", "wenden Basisfunktionen digitaler Medien (z. B. Computer, digitaler Fotoapparat) an."],
      "lom:header_datestamp": "2016-01-29T15:29:39Z",
      "lom:rights": "Gemeinfrei",
      "lom:educational_learningResourceType": ["simulation"],
      "lom:providerDate": ["2016-01-29T16:29:39+01:00"],
      "importDate": "2016-03-01T00:00:00+01:00",
      "lom:educational_intendedEndUserRole": ["learner"],
      "lom:creatorDate": ["2016-01-29T16:29:39+01:00"],
      "lom:general_title": "Wissensquiz zur Natur",
      "ll3:classificationCompetencyId": ["090401", "09040102", "09040104"],
      "lom:general_language": ["de"],
      "lom:relation_hasThumbnail": ["http://www.lerntraining-grundschule.de/sites/all/themes/om/grundschule/logo.png"]
    }
  }, {
    "_id": "DE:Mauswiesel.HE:164154",
    "_score": 0.29347447,
    "_source": {
      "lom:technical_location": "http://www.planet-schule.de/sf/php/02_sen01.php?sendung=746",
      "lom:creator": ["Friedhelm Schumacher"],
      "lom:educational_context": ["compulsory education", "primary school"],
      "lom:provider": ["Hessischer Bildungsserver"],
      "ll3:context": ["Allgemeinbildende Schule", "Primarstufe"],
      "ll3:classificationDisciplineEntry": ["Allgemeine Zoologie", "Biologie", "Grundschule", "Haustiere, Nutztiere", "Sachkunde", "Säugetiere", "Tiere", "Tiermonographie", "Wildlebende Tiere", "Wirbeltiere", "Zoologie"],
      "lom:classificationDisciplineEntry": ["Allgemeine Zoologie", "Tiermonographie", "Wildlebende Tiere"],
      "ll3:learningResourceType": ["Anderer Ressourcentyp"],
      "lom:header_datestamp": "2015-09-11T08:15:31Z",
      "lom:header_identifier": "DE:Mauswiesel.HE:164154",
      "lom:educational_learningResourceType": ["other"],
      "lom:rights_de": "Diese Ressource kann für unterrichtliche Zwecke genutzt werden.",
      "lom:providerDate": ["2015-09-11T10:15:31+02:00"],
      "ll3:classificationDisciplineId": ["080", "08005", "0800501", "0800504", "080050405", "08005040502", "280", "28010", "2801016", "280101601", "28010160101"],
      "importDate": "2016-03-01T00:00:00+01:00",
      "lom:general_title": "Der Igel als nachtaktives Säugetier",
      "lom:creatorDate": ["2015-09-11T10:15:31+02:00"],
      "lom:general_description": "Auf den Seiten des Schulfernsehens SWR und WDR Planet Schule finden Schülerinnen und Schüler einen Film über den Igel, den sie online anschauen können.",
      "lom:general_language": ["de"],
      "lom:relation_hasThumbnail": ["http://dms.bildung.hessen.de/dms_media/image/exercisefolder/mauswiesel/ergebnis_platzhalter.jpg"],
      "lom:classificationDisciplineId": ["0800501", "08005040502", "28010160101"]
    }
  }, {
    "_id": "DE:Mauswiesel.HE:169930",
    "_score": 0.29347447,
    "_source": {
      "lom:technical_location": "http://www.primolo.de/home/2a2b/",
      "lom:creator": ["Friedhelm Schumacher"],
      "lom:educational_context": ["compulsory education", "primary school"],
      "lom:provider": ["Hessischer Bildungsserver"],
      "ll3:context": ["Allgemeinbildende Schule", "Primarstufe"],
      "ll3:classificationDisciplineEntry": ["Allgemeine Zoologie", "Biologie", "Grundschule", "Haustiere, Nutztiere", "Sachkunde", "Säugetiere", "Tiere", "Tiermonographie", "Wildlebende Tiere", "Wirbeltiere", "Zoologie"],
      "lom:classificationDisciplineEntry": ["Allgemeine Zoologie", "Tiermonographie", "Wildlebende Tiere"],
      "ll3:learningResourceType": ["Anderer Ressourcentyp"],
      "lom:header_datestamp": "2012-01-16T22:10:14Z",
      "lom:header_identifier": "DE:Mauswiesel.HE:169930",
      "lom:educational_typicalAgeRange": ["7-9"],
      "lom:educational_learningResourceType": ["other"],
      "ll3:classificationDisciplineId": ["080", "08005", "0800501", "0800504", "080050405", "08005040502", "280", "28010", "2801016", "280101601", "28010160101"],
      "lom:providerDate": ["2012-01-16T23:10:14+01:00"],
      "lom:rights_de": "Diese Ressource kann für unterrichtliche Zwecke genutzt werden.",
      "lom:educational_intendedEndUserRole": ["student", "teacher"],
      "importDate": "2016-03-01T00:00:00+01:00",
      "lom:creatorDate": ["2012-01-16T23:10:14+01:00"],
      "lom:general_title": "Der Igel und das Mäuseken Wackelzahn",
      "lom:general_description": "Auf den Seiten von Primolo finden Sie eine Geschichte mit dem Titel \"Der Igel und das Mäuseken Wackelzahn\", geschrieben von Kindern einer zweiten Klasse.",
      "lom:general_keyword": ["Wackelzahn"],
      "lom:general_language": ["de"],
      "lom:classificationDisciplineId": ["0800501", "08005040502", "28010160101"],
      "lom:relation_hasThumbnail": ["http://dms.bildung.hessen.de/dms_media/image/exercisefolder/mauswiesel/ergebnis_platzhalter.jpg"]
    }
  }, {
    "_id": "DE:Mauswiesel.HE:124993",
    "_score": 0.1573544,
    "_source": {
      "lom:technical_location": "http://www.igelsos.de/was_nun/was_nun1.htm",
      "lom:creator": ["Friedhelm Schumacher"],
      "lom:educational_context": ["compulsory education", "primary school"],
      "lom:provider": ["Hessischer Bildungsserver"],
      "ll3:context": ["Allgemeinbildende Schule", "Primarstufe"],
      "ll3:classificationDisciplineEntry": ["Allgemeine Zoologie", "Biologie", "Grundschule", "Haustiere, Nutztiere", "Sachkunde", "Säugetiere", "Tiere", "Tiermonographie", "Wildlebende Tiere", "Wirbeltiere", "Zoologie"],
      "lom:classificationDisciplineEntry": ["Allgemeine Zoologie", "Tiermonographie", "Wildlebende Tiere"],
      "ll3:learningResourceType": ["Anderer Ressourcentyp"],
      "lom:header_datestamp": "2012-01-16T22:10:14Z",
      "lom:header_identifier": "DE:Mauswiesel.HE:124993",
      "lom:educational_typicalAgeRange": ["6-9"],
      "lom:educational_learningResourceType": ["other"],
      "ll3:classificationDisciplineId": ["080", "08005", "0800501", "0800504", "080050405", "08005040502", "280", "28010", "2801016", "280101601", "28010160101"],
      "lom:providerDate": ["2012-01-16T23:10:14+01:00"],
      "lom:rights_de": "Frei nutzbar",
      "lom:educational_intendedEndUserRole": ["student", "teacher"],
      "importDate": "2016-03-01T00:00:00+01:00",
      "lom:creatorDate": ["2012-01-16T23:10:14+01:00"],
      "lom:general_title": "Was nun kleiner Igel?",
      "lom:general_description": "Auf der Seite von igelsos.de finden Schülerinnen und Schüler eine kindgerechte Kurzanleitung zur Igelpflege mit anschaulichem Bildmaterial. Die Kurzanleitung liegt im pdf- Format zum kostenlosen Download zur Verfügung.",
      "lom:general_language": ["de"],
      "lom:classificationDisciplineId": ["0800501", "08005040502", "28010160101"],
      "lom:relation_hasThumbnail": ["http://dms.bildung.hessen.de/dms_media/image/exercisefolder/mauswiesel/ergebnis_platzhalter.jpg"]
    }
  }, {
    "_id": "LEARNLINE-00005780",
    "_score": 0.14103901,
    "_source": {
      "lom:technical_location": "http://www.pahaa.de/Hot_Potatoes/Sachkunde/Braunbrustigel.htm",
      "lom:provider": ["learn:line NRW"],
      "lom:classificationDisciplineEntry": ["Sachkunde"],
      "ll3:learningResourceType": ["Bild", "Simulation"],
      "lom:header_identifier": "LEARNLINE-00005780",
      "lom:educational_typicalAgeRange": ["6-9"],
      "ll3:classificationDisciplineId": ["280", "28010"],
      "lom:rights_de": "Die Lernhilfen stehen Interessierten (insbesondere Kindern, Eltern, Lehrern) für private und schulische Übungszwecke kostenlos zur Nutzung bereit. Eine kommerzielle Verwertung der angebotenen Lernmaterialien ist nicht gestattet.",
      "lom:ispartof": ["LEARNLINE-00005536"],
      "lom:general_description": "Es ist eine Online-Übung abrufbar, die sich interaktiv bearbeiten und automatisch auf Lösungsfehler überprüfen lässt.",
      "lom:general_keyword": ["Lernhilfen", "Lernmaterial", "Onlineübung", "interaktives Lernen", "Übungsmaterial"],
      "lom:classificationDisciplineId": ["28010"],
      "lom:educational_context": ["compulsory education", "primary school"],
      "lom:creator": ["Paul Haase"],
      "lom:publisher": ["Paul Haase"],
      "ll3:context": ["Allgemeinbildende Schule", "Primarstufe"],
      "lom:technical_format": "text/html",
      "ll3:classificationDisciplineEntry": ["Grundschule", "Sachkunde"],
      "lom:header_datestamp": "2014-06-13T11:14:17Z",
      "lom:rights": "CC-by-nc",
      "lom:educational_learningResourceType": ["image", "simulation"],
      "lom:providerDate": ["2014-06-13T13:14:17+02:00"],
      "lom:educational_intendedEndUserRole": ["learner", "teacher"],
      "importDate": "2016-03-01T00:00:00+01:00",
      "lom:general_title": "Online-Übungen zu Sachkunde (Säugetiere - Igel) (3. / 4. Schuljahr)",
      "lom:creatorDate": ["2014-06-13T13:14:17+02:00"],
      "lom:general_language": ["de"],
      "lom:relation_hasThumbnail": ["http://www.pahaa.de/images/Lernhilfen_Emblem.gif"]
    }
  }, {
    "_id": "LEARNLINE-00005181",
    "_score": 0.09662632,
    "_source": {
      "lom:technical_location": "http://www.bildungspartner.schulministerium.nrw.de/Bildungspartner/Praxisbeispiele/105_PB.pdf",
      "lom:provider": ["learn:line NRW"],
      "lom:classificationDisciplineEntry": ["Anlässe zum Sprechen, Lesen, Schreiben", "Biologie", "Deutsch", "Druckmedien", "Grundschule", "Lesen, Lesetechnik", "Lesen, Lesetechnik, Umgang mit Texten", "Medienerziehung", "Nichtliterarische Texte", "Pflanzen", "Sachgebietsübergreifende Medien", "Tiere", "Wildtiere"],
      "ll3:learningResourceType": ["Text"],
      "lom:header_identifier": "LEARNLINE-00005181",
      "lom:educational_typicalAgeRange": ["6-15"],
      "ll3:classificationDisciplineId": ["080", "120", "12003", "12007", "280", "28001", "2800101", "2800104", "28003", "28010", "2801015", "2801016", "280101602", "400", "40002", "4000201", "720"],
      "lom:general_description": "In Gruppenarbeit sammeln die Schülerinnen und Schüler in Büchern und dem Internet nach Informationen zum Thema Frühling.",
      "lom:general_keyword": ["Amphibien", "Außerschulischer Lernort", "Bibliothek", "Bildungspartner NRW", "Bildungspartnerschaft", "Eichhörnchen", "Frühling", "Igel", "Internet", "Jahreszeiten", "Kooperation", "Leseförderung", "Lesekompetenz", "Lesen", "Medienkompetenz", "Praxisbeispiel", "Recherchieren", "Vögel"],
      "lom:publisherDate": ["2013-11-30T01:00:00+01:00"],
      "lom:classificationDisciplineId": ["080", "120", "12003", "12007", "280", "28001", "2800101", "2800104", "28003", "2801015", "2801016", "280101602", "4000201", "720"],
      "lom:educational_context": ["compulsory education", "lower secondary school", "primary school"],
      "lom:creator": ["BIPA-Team"],
      "lom:publisher": ["Bibliothek und Schule", "Bildungspartner NRW", "Medienberatung NRW"],
      "ll3:context": ["Allgemeinbildende Schule", "Primarstufe", "Sekundarstufe I"],
      "lom:technical_format": "application/pdf",
      "ll3:classificationDisciplineEntry": ["Anlässe zum Sprechen, Lesen, Schreiben", "Biologie", "Deutsch", "Druckmedien", "Grundschule", "Lesen, Lesetechnik", "Lesen, Lesetechnik, Umgang mit Texten", "Medienerziehung", "Medienpädagogik", "Medienpädagogische Handlungsfelder", "Nichtliterarische Texte", "Pflanzen", "Sachgebietsübergreifende Medien", "Sachkunde", "Tiere", "Wildtiere"],
      "lom:header_datestamp": "2014-09-19T16:12:20Z",
      "lom:rights": "CC-by-sa",
      "lom:educational_learningResourceType": ["text"],
      "lom:providerDate": ["2014-09-19T18:12:20+02:00"],
      "lom:educational_intendedEndUserRole": ["teacher"],
      "importDate": "2016-03-01T00:00:00+01:00",
      "lom:general_title": "Praxisbeispiel: Unterricht in der Bibliothek - Frühling",
      "lom:creatorDate": ["2014-09-19T18:12:20+02:00"],
      "lom:general_language": ["de"],
      "lom:relation_hasThumbnail": ["http://www.bildungspartner.schulministerium.nrw.de/Bildungspartner/Praxisbeispiele/BP_NRW_Bildmarke_RGB_100_final9-2.jpg"]
    }
  }, {
    "_id": "SN-05559606",
    "_score": 0.09285698,
    "_source": {
      "lom:technical_location": "http://lexi-online.de/themen/tierwelt/winterschlaf",
      "lom:provider": ["MeSax"],
      "lom:classificationDisciplineEntry": ["Sinnesorgane, Nervensystem", "Verhalten", "Wildlebende Tiere"],
      "ll3:learningResourceType": ["Text"],
      "lom:header_identifier": "SN-05559606",
      "lom:educational_typicalAgeRange": ["10-18"],
      "lom:isparentof": ["lexi-tv|:|:|:|BY-00001154"],
      "ll3:classificationDisciplineId": ["080", "08005", "0800504", "080050405", "08005040502", "08006", "0800603", "0800607"],
      "lom:ispartof": ["BY-00000893"],
      "lom:general_description": "Neidvoll schaut der Mensch im Winter auf die Tierwelt: statt sich um steigende Energiepreise zu sorgen und Winterdepressionen zu kultivieren, kann ein Großteil der Fauna im Winter einfach das Licht ausmachen und sich auf die faule Haut legen. Um den Traum auch für den Menschen wahr zu machen, sind Wissenschaftler dem Winterschlafhormon H.I.T. auf der Spur. LexiTV berichtet über den Schlummerwirkstoff.",
      "lom:general_keyword": ["Fledermäuse", "Gefühl", "Igel", "Murmeltiere", "Säugetiere", "Verhalten (Tier)", "Wahrnehmung (Sinnesorgan)", "Winterschlaf"],
      "lom:publisherDate": ["2009-11-30T01:00:00+01:00"],
      "lom:classificationDisciplineId": ["08005040502", "0800603", "0800607"],
      "lom:educational_context": ["compulsory education", "lower secondary school", "special education", "upper secondary school"],
      "lom:creator": ["Frank Frenzel"],
      "lom:publisher": ["MDR"],
      "ll3:context": ["Allgemeinbildende Schule", "Sekundarstufe I", "Sekundarstufe II", "Sonderpädagogische Förderung"],
      "lom:technical_format": "text/html",
      "ll3:classificationDisciplineEntry": ["Biologie", "Menschenkunde", "Sinnesorgane, Nervensystem", "Säugetiere", "Verhalten", "Wildlebende Tiere", "Wirbeltiere", "Zoologie"],
      "lom:header_datestamp": "2015-05-18T20:39:18Z",
      "lom:rights": "keine Angabe",
      "lom:educational_learningResourceType": ["text"],
      "lom:providerDate": ["2015-05-18T22:39:18+02:00"],
      "lom:educational_intendedEndUserRole": ["learner", "teacher"],
      "importDate": "2016-03-01T00:00:00+01:00",
      "lom:creatorDate": ["2015-05-18T22:39:18+02:00"],
      "lom:general_title": "Winterschlaf",
      "lom:general_language": ["de"],
      "lom:relation_hasThumbnail": ["http://lexi-online.de/fileadmin/user_upload/image/themen/thema_362_1.jpg"]
    }
  }, {
    "_id": "BY-00001153",
    "_score": 0.08214271,
    "_source": {
      "lom:technical_location": "http://lexi-online.de/themen/tierwelt/winterschlaf/auf_sparflamme",
      "lom:classificationDisciplineEntry": ["Verhalten", "Wildlebende Tiere"],
      "ll3:learningResourceType": ["Text"],
      "lom:header_identifier": "BY-00001153",
      "lom:educational_typicalAgeRange": ["10-18"],
      "ll3:classificationDisciplineId": ["080", "08005", "0800501", "080050104", "0800504", "080050405", "08005040502"],
      "lom:ispartof": ["SN-05559606"],
      "lom:general_description": "Der Siebenschläfer tut es, die Fledermaus, das Murmeltier - sie alle verabschieden sich in der kalten Jahreszeit von den Wachenden und machen drei bis sieben Monate Pause.",
      "lom:general_keyword": ["Fledermaus", "Gefühl", "Igel", "Kältestarre", "Murmeltier", "Nagetier", "Sommerschlaf", "Säugetier", "Verhalten ( Tier)", "Wahrnehmung ( Sinnesorgan)", "Warmblüter", "Winterruhe", "Winterschlaf", "Winterstarre"],
      "lom:publisherDate": ["2009-11-30T01:00:00+01:00"],
      "lom:ischildof": "lexi-tv|:|:|:|SN-05559606",
      "lom:classificationDisciplineId": ["080050104", "08005040502"],
      "lom:educational_context": ["compulsory education", "lower secondary school", "special education", "upper secondary school"],
      "lom:creator": ["Hartmut Wermann"],
      "lom:publisher": ["MDR"],
      "ll3:context": ["Allgemeinbildende Schule", "Sekundarstufe I", "Sekundarstufe II", "Sonderpädagogische Förderung"],
      "ll3:classificationDisciplineEntry": ["Allgemeine Zoologie", "Biologie", "Säugetiere", "Verhalten", "Wildlebende Tiere", "Wirbeltiere", "Zoologie"],
      "lom:technical_format": "text/html",
      "lom:header_datestamp": "2014-10-21T21:04:38Z",
      "lom:educational_learningResourceType": ["text"],
      "importDate": "2016-03-01T00:00:00+01:00",
      "lom:educational_intendedEndUserRole": ["learner", "teacher"],
      "lom:general_title": "Auf Sparflamme",
      "lom:creatorDate": ["2014-10-21T23:04:38+02:00"],
      "lom:general_language": ["de"],
      "lom:relation_hasThumbnail": ["http://lexi-online.de/fileadmin/user_upload/image/artikel/thumb_458_181796dbf1fe58edb193f0bb98558933.jpg"]
    }
  }, {
    "_id": "LEARNLINE-00005774",
    "_score": 0.078281716,
    "_source": {
      "lom:technical_location": "http://www.pahaa.de/Bildergalerie/index_Saeugetiere1.htm",
      "lom:provider": ["learn:line NRW"],
      "lom:classificationDisciplineEntry": ["Sachkunde"],
      "ll3:learningResourceType": ["Bild", "Simulation", "Video"],
      "lom:header_identifier": "LEARNLINE-00005774",
      "lom:educational_typicalAgeRange": ["6-9"],
      "lom:rights_de": "Die Lernhilfen stehen Interessierten (insbesondere Kindern, Eltern, Lehrern) für private und schulische Übungszwecke kostenlos zur Nutzung bereit. Eine kommerzielle Verwertung der angebotenen Lernmaterialien ist nicht gestattet.",
      "ll3:classificationDisciplineId": ["280", "28010"],
      "lom:ispartof": ["LEARNLINE-00005536"],
      "lom:general_description": "Zu dem Thema gibt es eine Bildergalerie. Außerdem sind 5 Online-Übungen abrufbar, die sich interaktiv bearbeiten und automatisch auf Lösungsfehler überprüfen lassen. Mit Rotfuchs, Wildschwein, Dachs, Feldhasen und Igel beschäftigt sich jeweils eine dieser Übungen. Mehrere Links verweisen auf themenbezogene YouTube-Videos.",
      "lom:general_keyword": ["Lernhilfen", "Lernmaterial", "Onlineübung", "interaktives Lernen", "Übungsmaterial"],
      "lom:ischildof": "learnline|:|:|:|LEARNLINE-00005536",
      "lom:classificationDisciplineId": ["28010"],
      "lom:educational_context": ["compulsory education", "primary school"],
      "lom:creator": ["Paul Haase"],
      "lom:publisher": ["Paul Haase"],
      "ll3:context": ["Allgemeinbildende Schule", "Primarstufe"],
      "lom:technical_format": "text/html",
      "ll3:classificationDisciplineEntry": ["Grundschule", "Sachkunde"],
      "lom:header_datestamp": "2014-06-13T10:27:32Z",
      "lom:rights": "CC-by-nc",
      "lom:educational_learningResourceType": ["image", "simulation", "video"],
      "lom:providerDate": ["2014-06-13T12:27:32+02:00"],
      "lom:educational_intendedEndUserRole": ["learner", "teacher"],
      "importDate": "2016-03-01T00:00:00+01:00",
      "lom:creatorDate": ["2014-06-13T12:27:32+02:00"],
      "lom:general_title": "Online-Übungen und Bildergalerie zu Sachkunde (Säugetiere - Wildtiere in Mitteleuropa) (3. / 4. Schuljahr)",
      "lom:general_language": ["de"],
      "lom:relation_hasThumbnail": ["http://www.pahaa.de/images/Lernhilfen_Emblem.gif"]
    }
  }]
}
undefined
